klaviyo_mcp_server/__init__.py
klaviyo_mcp_server/main.py
klaviyo_mcp_server/models/campaigns/__init__.py
klaviyo_mcp_server/models/campaigns/models.py
klaviyo_mcp_server/models/events/__init__.py
klaviyo_mcp_server/models/events/models.py
klaviyo_mcp_server/models/profiles/__init__.py
klaviyo_mcp_server/models/profiles/models.py
klaviyo_mcp_server/models/reporting/__init__.py
klaviyo_mcp_server/models/reporting/models.py
klaviyo_mcp_server/prompts/__init__.py
klaviyo_mcp_server/prompts/reporting_prompts.py
klaviyo_mcp_server/scripts/__init__.py
klaviyo_mcp_server/scripts/run_client_secure.py
klaviyo_mcp_server/server.py
klaviyo_mcp_server/tools/__init__.py
klaviyo_mcp_server/tools/accounts.py
klaviyo_mcp_server/tools/campaigns.py
klaviyo_mcp_server/tools/catalogs.py
klaviyo_mcp_server/tools/events.py
klaviyo_mcp_server/tools/flows.py
klaviyo_mcp_server/tools/images.py
klaviyo_mcp_server/tools/lists.py
klaviyo_mcp_server/tools/metrics.py
klaviyo_mcp_server/tools/profiles.py
klaviyo_mcp_server/tools/reporting.py
klaviyo_mcp_server/tools/segments.py
klaviyo_mcp_server/tools/subscriptions.py
klaviyo_mcp_server/tools/templates.py
klaviyo_mcp_server/utils/__init__.py
klaviyo_mcp_server/utils/add_related_data.py
klaviyo_mcp_server/utils/filter_utils.py
klaviyo_mcp_server/utils/generate_model_from_oas.py
klaviyo_mcp_server/utils/param_types.py
klaviyo_mcp_server/utils/reporting_utils.py
klaviyo_mcp_server/utils/tool_decorator.py
klaviyo_mcp_server/utils/utils.py
klaviyo_mcp_server/version.py
klaviyo_mcp_server-0.4.0.dist-info/licenses/LICENSE
klaviyo_mcp_server-0.4.0.dist-info/WHEEL
klaviyo_mcp_server-0.4.0.dist-info/entry_points.txt
klaviyo_mcp_server-0.4.0.dist-info/METADATA
klaviyo_mcp_server-0.4.0.dist-info/RECORD
