Metadata-Version: 2.4
Name: klaviyo-mcp-server
Version: 0.4.0
Summary: Klaviyo MCP Server
Keywords: ai,klaviyo ai,mcp,Klaviyo,Klaviyo api
Author: Klaviyo Developer Experience Team
Author-email: Klaviyo Developer Experience Team <developers@klaviyo.com>
License-File: LICENSE
Requires-Dist: faker>=37.4.0
Requires-Dist: fastmcp>=2.8.0
Requires-Dist: httpx>=0.28.1
Requires-Dist: klaviyo-api>=19.0.2
Requires-Dist: orjson>=3.10.18
Requires-Dist: pre-commit>=4.2.0
Requires-Dist: psutil>=7.0.0
Requires-Dist: pytest>=8.4.0
Requires-Dist: pytest-asyncio>=1.0.0
Requires-Dist: requests>=2.32.4
Requires-Python: >=3.13
